async_task_processor/__init__.py
async_task_processor/async_task_processor.py
async_task_processor/models.py
async_task_processor/utils.py
tests/__init__.py
tests/test_async_task_processor.py
toms_async_task_processor-0.1.0.dist-info/LICENSE
toms_async_task_processor-0.1.0.dist-info/METADATA
toms_async_task_processor-0.1.0.dist-info/WHEEL
toms_async_task_processor-0.1.0.dist-info/top_level.txt
toms_async_task_processor-0.1.0.dist-info/RECORD
