Metadata-Version: 2.1
Name: toms_async_task_processor
Version: 0.1.0
Summary: A simple asynchronous task processor
Home-page: https://github.com/tomsamwel/AsyncTaskProcessor.git
Author: Tom Samwel
Author-email: tommiesamwel@gmail.com
Classifier: Programming Language :: Python :: 3
Classifier: License :: OSI Approved :: MIT License
Classifier: Operating System :: OS Independent
Requires-Python: >=3.7
License-File: LICENSE
Requires-Dist: pydantic >=1.8.2
Requires-Dist: pytest >=6.2.5
Requires-Dist: pytest-asyncio >=0.15.1
